{
  "response": [
    {
        "maintainer": "Krell RHEL (WolfAURman)",
        "oem": "Xiaomi",
        "device": "Redmi 7",
        "filename": "crDroidAndroid-11.0-20221012-onclite-v7.23.zip",
        "download": "https://github.com/WolfAURman/crdroid_ota_update/releases/download/crDroidAndroid-11.0-20221012-onclite-v7.23/crDroidAndroid-11.0-20221012-onclite-v7.23.zip",
        "timestamp": 1665540039,
        "md5": "6e89db2049043284e27e41ad6278790e",
        "size": 912879608,
        "version": "7.23",
        "buildtype": "Monthly",
        "forum": "https://t.me/WolfAURman_Discussion",
        "gapps": "https://sourceforge.net/projects/nikgapps/files/Releases/NikGapps-R/08-Sep-2022/NikGapps-core-arm64-11-20220908-signed.zip/download",
        "firmware": "",
        "modem": "",
        "bootloader": "",
        "recovery": "",
        "paypal": "http://paypal.me/rozenov",
        "telegram": "https://t.me/red_hat_interprise13"
    }
  ]
}
