{
  "response": [
    {
        "maintainer": "Krell RHEL (WolfAURman)",
        "oem": "Xiaomi",
        "device": "Redmi 6 Pro",
        "filename": "crDroidAndroid-13.0-20221110-sakura-v9.0.zip",
        "download": "https://github.com/WolfAURman/crdroid_ota_update/releases/download/crDroidAndroid-13.0-20221110-sakura-v9.0/crDroidAndroid-13.0-20221110-sakura-v9.0.zip",
        "timestamp": 1668064641,
        "md5": "e36fa22a2290e3708dc7118efe04278f",
        "sha256": "bc5a2dc320de671805d32ada97d7b3e9c2c39df6c297c3e91824e0c0c0406b40",
        "size": 851839970,
        "version": "9.0",
        "buildtype": "Monthly",
        "forum": "https://t.me/WolfAURman_Discussion",
        "gapps": "https://sourceforge.net/projects/nikgapps/files/Releases/NikGapps-T/08-Sep-2022/NikGapps-core-arm64-13-20220908-signed.zip/download",
        "firmware": "",
        "modem": "",
        "bootloader": "",
        "recovery": "",
        "paypal": "http://paypal.me/rozenov",
        "telegram": "https://t.me/red_hat_interprise13",
        "dt": "",
        "common-dt": "",
        "kernel": ""
    }
  ]
}
